Workbook

Sheet Feuille 1
A1: No | B1: No
A2: 1 | B2: 1.1 | C2: ENTREPRENEURS | D2: STATUT | E2: ASSO. | F2: CHANTIER COMMUN EN PREPA | G2: CHANTIER ANTICIPE | J2: MOB | K2: FALSE
A3: 1.5 | B3: 1.2 | C3: BA.R | F3: ECURIES | J3: SOLIVAGE | K3: FALSE
A4: 2 | B4: 1.3 | C4: Simon | F4: ECURIES | J4: CHARPENTE | K4: FALSE
A5: 2.5 | B5: 1.4 | J5: ISOLATION | K5: TRUE
A6: 3 | B6: 1.5 | J6: CHEVRONS | K6: TRUE
A7: 3.5 | B7: 1.6 | C7: =F2 -> CHANTIER COMMUN EN PREPA | D7: =F3 -> ECURIES | J7: HPV | K7: TRUE
A8: 4 | B8: 1.7 | C8: Déscripton du chantier: | D8: localité: | E8: Effectif: | F8: Logistique | G8: Levage | H8: Sécurité | I8: Accès | J8: LATTES | K8: TRUE
A9: 4.5 | B9: 1.8 | C9: Projet de rénovation d'un garage en studio; surface au sol 38 m², action menés: réféction de toiture | D9: Sainte-foy de Peyrolière | E9: 2 | F9: Livraison fournisseur sur chantier | G9: Non, réutilisation des tuiles, stockage sur plateforme echaffaudée | H9: Echaffaudage bas de pente, plateforme 9m² stockage tuile | I9: Echaffaudage | J9: LITEAUX | K9: TRUE
A10: 5 | B10: 1.9 | C10: Tableau des valeurs à remplir (couverture) | E10: Tableau des valeurs à remplir (MOB) | J10: TUILES | K10: TRUE
A11: 5.5 | B11: 2 | C11: Mètre carrés de couverture: | D11: 450 | E11: Mètre linéaire de murs: | F11: No | J11: FAITAGE | K11: TRUE
A12: 6 | B12: 2.1 | C12: Pente: | D12: 28 | E12: Hauteur au faitage: | F12: No | J12: ARETIERS | K12: TRUE
A13: 6.5 | B13: 2.2 | C13: Hauteur à l'égout: | D13: 3 | J13: NOUES | K13: FALSE
A14: 7 | B14: 2.3 | C14: Accès: | D14: Possible echaff
A15: 7.5 | B15: 2.4
A16: 8 | B16: 2.5
A17: 8.5 | B17: 2.6
A18: 9 | B18: 2.7 | C18: =J2 -> MOB | E18: =J3 -> SOLIVAGE | G18: =J4 -> CHARPENTE | I18: =J5 -> ISOLATION | K18: =J6 -> CHEVRONS | M18: =J7 -> HPV | O18: =J8 -> LATTES | Q18: =J9 -> LITEAUX | S18: =J10 -> TUILES | U18: =J11 -> FAITAGE | W18: =J12 -> ARETIERS | Y18: =J13 -> NOUES
A19: 9.5 | B19: 2.8 | C19: Montants | D19: No | E19: PORTEUSES | F19: No | G19: C18 | H19: 100×200 | I19: Sarking | J19: =D11 -> 450 | K19: C18 | L19: 63×100 | M19: HPV | N19: ECRAN R2 HPV 50/1,50M ELOS | O19: C18 | P19: 18×44 | Q19: C18 | R19: LITEAUX sapin 3X4cm | S19: TERREAL | T19: TERREAL - DC12 Double Canal 12 | U19: ML | V19: 30 | W19: ML | X19: 20 | Y19: ML | Z19: 6
A20: 10 | B20: 2.9 | C20: Lisses | D20: No | E20: SOLIVES | F20: No | G20: C24/C30 | H20: 75 × 225 | I20: ISO ENTRE CHEVRONS | J20: No | K20: C24/C30 | L20: No | S20: EDILIANS
A21: 10.5 | B21: 3 | C21: CTVT | D21: No | E21: PLANCHE | F21: No | I21: TRI-ISO | J21: No | K21: Volige | L21: VOLIGES 15mm TR2 TTL ( toutes largeurs )
A22: 11 | B22: 3.1 | C22: EAU INT | D22: No | I22: AUTRES | J22: No
A23: 11.5 | B23: 3.2 | C23: EAU EXT | D23: No
A24: 12 | B24: 3.3 | C24: Sous-Lisses | D24: No
A25: 12.5 | B25: 3.4
A26: 13 | B26: 3.5 | C26: Désignation | E26: def | F26: ref calcul/quantitatif | H26: Coût unitaire TTC | J26: Charge | K26: Marge | L26: Revente facturé | M26: Temps de pose /h | N26: taux | O26: Presta facturé | P26: Total facturé
A27: 13.5 | B27: 3.6 | C27: MOB | D27: =C19 -> Montants | E27: =D19 -> No | F27: =IF(D19="No","No",(F11*D13)*2.2) -> No | G27: /ml | H27: =ifs(D19='Feuille 2'!C34,2.5,D19='Feuille 2'!C43,'Feuille 2'!G43,D19='Feuille 2'!C44,'Feuille 2'!G6,D19='Feuille 2'!C45,'Feuille 2'!G7,D19="No","No") -> No | I27: ml | J27: 0.15 | K27: 0.1 | L27: =IF(F27="No","No",((H27*F27)*(1+J27))*(K27+1)) -> No | M27: =IF(E27="No","No",F27/40) -> No | N27: =500/7 -> 71.428571 | O27: =IF(L27="No","No",(L27*0.1)+(N27*M27)) -> No | P27: =IF(O27="No","No",O27+L27) -> No
A28: 14 | B28: 3.7 | D28: =C20 -> Lisses | E28: =D20 -> No | F28: =IF(D20="No","No",F11*2.5) -> No | G28: /ml | H28: =ifs(D20='Feuille 2'!C35,2.5,D20='Feuille 2'!C44,'Feuille 2'!G44,D20='Feuille 2'!C45,'Feuille 2'!G7,D20='Feuille 2'!C46,'Feuille 2'!G8,D20="No","No") -> No | I28: ml | J28: 0.15 | K28: 0.1 | L28: =IF(F28="No","No",((H28*F28)*(1+J28))*(K28+1)) -> No | M28: =IF(E28="No","No",F28/40) -> No | O28: =IF(L28="No","No",(L28*0.1)+(N28*M28)) -> No | P28: =IF(O28="No","No",O28+L28) -> No
A29: 14.5 | B29: 3.8 | D29: =C21 -> CTVT | E29: =D21 -> No | F29: =IF(F12="No","No",(F12*D13)*1.2) -> No | G29: /m² | H29: =ifs(D21='Feuille 2'!A8,'Feuille 2'!G15,D21="No","No") -> No | I29: =G29 -> /m² | J29: 0.15 | K29: 0.1 | L29: =IF(F29="No","No",((H29*F29)*(1+J29))*(K29+1)) -> No | M29: =IF(E29="No","No",F29/40) -> No | O29: =IF(L29="No","No",(L29*0.1)+(N29*M29)) -> No | P29: =IF(O29="No","No",O29+L29) -> No
A30: 15 | B30: 3.9 | D30: =C22 -> EAU INT | E30: =D22 -> No | F30: =IF(F12="No","No",(F12*D13)*1.2) -> No | G30: /m² | I30: =G30 -> /m² | J30: 0.15 | K30: 0.1 | L30: =IF(F30="No","No",((H30*F30)*(1+J30))*(K30+1)) -> No | M30: =IF(E30="No","No",F30/40) -> No | O30: =IF(L30="No","No",(L30*0.1)+(N30*M30)) -> No | P30: =IF(O30="No","No",O30+L30) -> No
A31: 15.5 | B31: 4 | D31: =C23 -> EAU EXT | E31: =D23 -> No | F31: =IF(F12="No","No",(F12*D13)*1.2) -> No | G31: /m² | I31: =G31 -> /m² | J31: 0.15 | K31: 0.1 | L31: =IF(F31="No","No",((H31*F31)*(1+J31))*(K31+1)) -> No | M31: =IF(E31="No","No",F31/40) -> No | O31: =IF(L31="No","No",(L31*0.1)+(N31*M31)) -> No | P31: =IF(O31="No","No",O31+L31) -> No
A32: 16 | B32: 4.1 | D32: =C24 -> Sous-Lisses | E32: =D24 -> No | F32: =IF(D24="No","No",D24*2.2) -> No | G32: /ml | I32: =G32 -> /ml | J32: 0.15 | K32: 0.1 | L32: =IF(F32="No","No",((H32*F32)*(1+J32))*(K32+1)) -> No | M32: =IF(E32="No","No",F32/40) -> No | O32: =IF(L32="No","No",(L32*0.1)+(N32*M32)) -> No | P32: =IF(O32="No","No",O32+L32) -> No
A33: 16.5 | B33: 4.2 | C33: SOLIVAGE | D33: =E19 -> PORTEUSES | E33: =F19 -> No | F33: No | G33: /ml | I33: =G33 -> /ml | J33: 0.15 | K33: 0.1 | L33: =IF(F33="No","No",((H33*F33)*(1+J33))*(K33+1)) -> No | M33: No | N33: =500/7 -> 71.428571 | O33: =IF(L33="No","No",(L33*0.1)+(N33*M33)) -> No | P33: =IF(O33="No","No",O33+L33) -> No
A34: 17 | B34: 4.3 | D34: =E20 -> SOLIVES | E34: =F20 -> No | F34: No | G34: /ml | I34: =G34 -> /ml | J34: 0.15 | K34: 0.1 | L34: =IF(F34="No","No",((H34*F34)*(1+J34))*(K34+1)) -> No | O34: =IF(L34="No","No",(L34*0.1)+(N34*M34)) -> No | P34: =IF(O34="No","No",O34+L34) -> No
A35: 17.5 | B35: 4.4 | D35: =E21 -> PLANCHE | E35: =F21 -> No | F35: No | G35: /m² | I35: =G35 -> /m² | J35: 0.15 | K35: 0.1 | L35: =IF(F35="No","No",((H35*F35)*(1+J35))*(K35+1)) -> No | M35: No | N35: =500/7 -> 71.428571 | O35: =IF(L35="No","No",(L35*0.1)+(N35*M35)) -> No | P35: =IF(O35="No","No",O35+L35) -> No
A36: 18 | B36: 4.5 | C36: CHARPENTE | D36: =G19 -> C18 | E36: =H19 -> 100×200 | F36: No | G36: /ml | H36: =ifs(E36='Feuille 2'!C38,"no",E36='Feuille 2'!C30,'Feuille 2'!G30,E36='Feuille 2'!C31,'Feuille 2'!G31,E36='Feuille 2'!C32,'Feuille 2'!G32,E36='Feuille 2'!C33,'Feuille 2'!G33,E36='Feuille 2'!C34,'Feuille 2'!G34,E36='Feuille 2'!C35,'Feuille 2'!G35,E36='Feuille 2'!C36,'Feuille 2'!G36,E36='Feuille 2'!C37,'Feuille 2'!G37) -> 9.1 | I36: =G36 -> /ml | J36: 0.15 | K36: 0.1 | L36: =IF(F36="No","No",((H36*F36)*(1+J36))*(K36+1)) -> No | M36: 16 | N36: =500/7 -> 71.428571 | O36: =IF(L36="No","No",(L36*0.1)+(N36*M36)) -> No | P36: =IF(O36="No","No",O36+L36) -> No
A37: 18.5 | B37: 4.6 | D37: =G20 -> C24/C30 | E37: =H20 -> 75 × 225 | F37: 30 | G37: /ml | H37: =ifs(E37='Feuille 2'!C39,'Feuille 2'!G39,E37='Feuille 2'!C38,"No",E37='Feuille 2'!C40,'Feuille 2'!G40,E37='Feuille 2'!C41,'Feuille 2'!G41,E37='Feuille 2'!C42,'Feuille 2'!G42,E37='Feuille 2'!C43,'Feuille 2'!G43,E37='Feuille 2'!C44,'Feuille 2'!G44,E37='Feuille 2'!C45,'Feuille 2'!G45,E37='Feuille 2'!C46,'Feuille 2'!G46,E37='Feuille 2'!C47,'Feuille 2'!G47,E37='Feuille 2'!C48,'Feuille 2'!G48,E37='Feuille 2'!C49,'Feuille 2'!G49,E37='Feuille 2'!C50,'Feuille 2'!G50) -> 15.886 | I37: =G37 -> /ml | J37: 0.15 | K37: 0.1 | L37: =IF(F37="No","No",((H37*F37)*(1+J37))*(K37+1)) -> 602.8737 | O37: =IF(L37="No","No",(L37*0.1)+(N37*M37)) -> 60.28737 | P37: =IF(O37="No","No",O37+L37) -> 663.16107
A38: 19 | B38: 4.7 | C38: ISOLATION | D38: =I19 -> Sarking | E38: =J19 -> 450 | F38: =E38 -> 450 | G38: /m² | H38: 31 | I38: =G38 -> /m² | J38: 0.15 | K38: 0.1 | L38: =IF(F38="No","No",((H38*F38)*(1+J38))*(K38+1)) -> 17646.75 | M38: 80 | N38: =500/7 -> 71.428571 | O38: =IF(L38="No","No",(L38*0.1)+(N38*M38)) -> 7478.9607 | P38: =IF(O38="No","No",O38+L38) -> 25125.711
A39: 19.5 | B39: 4.8 | D39: =I20 -> ISO ENTRE CHEVRONS | E39: =J20 -> No | F39: =IF(J20="No","No",D12*0.9) -> No | G39: /m² | I39: =G39 -> /m² | J39: 0.15 | K39: 0.1 | L39: =IF(F39="No","No",((H39*F39)*(1+J39))*(K39+1)) -> No | O39: =IF(L39="No","No",(L39*0.1)+(N39*M39)) -> No | P39: =IF(O39="No","No",O39+L39) -> No
A40: 20 | B40: 4.9 | D40: =I21 -> TRI-ISO | E40: =J21 -> No | F40: =IF(J21="No","No",D13*1.15) -> No | G40: /m² | I40: =G40 -> /m² | J40: 0.15 | K40: 0.1 | L40: =IF(F40="No","No",((H40*F40)*(1+J40))*(K40+1)) -> No | M40: No | O40: =IF(L40="No","No",(L40*0.1)+(N40*M40)) -> No | P40: =IF(O40="No","No",O40+L40) -> No
A41: 21 | B41: 5 | D41: =I22 -> AUTRES | E41: =J22 -> No | F41: =IF(J22="No","No",D11*1.15) -> No | G41: /m² | I41: =G41 -> /m² | J41: 0.15 | K41: 0.1 | L41: =IF(F41="No","No",((H41*F41)*(1+J41))*(K41+1)) -> No | O41: =IF(L41="No","No",(L41*0.1)+(N41*M41)) -> No | P41: =IF(O41="No","No",O41+L41) -> No
A42: 22 | B42: 5.1 | C42: CHEVRONS | D42: =K19 -> C18 | E42: =L19 -> 63×100 | F42: 50 | G42: /ml | H42: =ifs(E42='Feuille 2'!C38,"No",E42='Feuille 2'!C34,'Feuille 2'!G34,E42='Feuille 2'!C35,'Feuille 2'!G35,E42='Feuille 2'!C36,'Feuille 2'!G36) -> 2.86 | I42: =G42 -> /ml | J42: 0.15 | K42: 0.1 | L42: =IF(F42="No","No",((H42*F42)*(1+J42))*(K42+1)) -> 180.895 | M42: =(F48/60)*4*8 -> 240 | N42: =500/7 -> 71.428571 | O42: =IF(L42="No","No",(L42*0.1)+(N42*M42)) -> 17160.947 | P42: =IF(O42="No","No",O42+L42) -> 17341.842
A43: 23 | B43: 5.2 | D43: =K20 -> C24/C30 | E43: =L20 -> No | F43: No | G43: /ml | H43: =ifs(E43='Feuille 2'!C42,'Feuille 2'!G42,E43='Feuille 2'!C38,"No",E43='Feuille 2'!C43,'Feuille 2'!G43,E43='Feuille 2'!C44,'Feuille 2'!G44,E43='Feuille 2'!C45,'Feuille 2'!G45) -> No | I43: =G43 -> /ml | J43: 0.15 | K43: 0.1 | L43: =IF(F43="No","No",((H43*F43)*(1+J43))*(K43+1)) -> No | O43: =IF(L43="No","No",(L43*0.1)+(N43*M43)) -> No | P43: =IF(O43="No","No",O43+L43) -> No
A44: 24 | B44: 5.3 | C44: HPV | D44: =M19 -> HPV | E44: =N19 -> ECRAN R2 HPV 50/1,50M ELOS | G44: /m² | H44: =ifs(E44='Feuille 2'!A15,'Feuille 2'!G15/75,E44="No","No") -> 1.3885333 | I44: =G44 -> /m² | J44: 0.15 | K44: 0.1 | L44: =IF(F44="No","No",((H44*F44)*(1+J44))*(K44+1)) -> 0 | N44: =500/7 -> 71.428571 | O44: =IF(L44="No","No",(L44*0.1)+(N44*M44)) -> 0 | P44: =IF(O44="No","No",O44+L44) -> 0
A45: 25 | B45: 5.4 | C45: LATTES | D45: =O19 -> C18 | E45: =P19 -> 18×44 | F45: =IF(P19="No","No",D11*2.5) -> 1125 | G45: /ml | H45: =ifs(E45='Feuille 2'!C30,'Feuille 2'!G30,E45='Feuille 2'!C31,'Feuille 2'!G31,E45="No","No") -> 0.52 | I45: =G45 -> /ml | J45: 0.15 | K45: 0.1 | L45: =IF(F45="No","No",((H45*F45)*(1+J45))*(K45+1)) -> 740.025 | O45: =IF(L45="No","No",(L45*0.1)+(N45*M45)) -> 74.0025 | P45: =IF(O45="No","No",O45+L45) -> 814.0275
A46: 26 | B46: 5.5 | C46: VOLIGE | D46: C18 | E46: =L21 -> VOLIGES 15mm TR2 TTL ( toutes largeurs ) | F46: 50 | G46: /m² | H46: =ifs(E46='Feuille 2'!A67,'Feuille 2'!G67,E46='Feuille 2'!A68,'Feuille 2'!G68,E46="No","No") -> 6.435 | I46: =G46 -> /m² | J46: 0.15 | K46: 0.1 | L46: =IF(F46="No","No",((H46*F46)*(1+J46))*(K46+1)) -> 407.01375 | O46: =IF(L46="No","No",(L46*0.1)+(N46*M46)) -> 40.701375 | P46: =IF(O46="No","No",O46+L46) -> 447.71513
A47: 27 | B47: 5.6 | C47: LITEAUX | D47: =Q19 -> C18 | E47: =R19 -> LITEAUX sapin 3X4cm | F47: =IF(P20="No","No",D11*3.3) -> 1485 | G47: /ml | H47: =ifs(E47='Feuille 2'!A71,'Feuille 2'!G71,E47="No","No") -> 0.624 | I47: =G47 -> /ml | J47: 0.15 | K47: 0.1 | L47: =IF(F47="No","No",((H47*F47)*(1+J47))*(K47+1)) -> 1172.1996 | O47: =IF(L47="No","No",(L47*0.1)+(N47*M47)) -> 117.21996 | P47: =IF(O47="No","No",O47+L47) -> 1289.4196
A48: 28 | B48: 5.7 | C48: TUILES | D48: =S19 -> TERREAL | E48: =T19 -> TERREAL - DC12 Double Canal 12 | F48: =D11 -> 450 | G48: m² | H48: 18 | I48: /m² | J48: 0.15 | K48: 0.1 | L48: =IF(F48="No","No",((H48*F48)*(1+J48))*(K48+1)) -> 10246.5 | N48: =500/7 -> 71.428571 | O48: =IF(L48="No","No",(L48*0.1)+(N48*M48)) -> 1024.65 | P48: =IF(O48="No","No",O48+L48) -> 11271.15
A49: 29 | B49: 5.8 | C49: FAITAGE | D49: =D48 -> TERREAL | E49: =V19 -> 30 | F49: =E49 -> 30 | G49: ml | H49: 16 | I49: /ml | J49: 0.15 | K49: 0.1 | L49: =IF(F49="No","No",((H49*F49)*(1+J49))*(K49+1)) -> 607.2 | N49: =500/7 -> 71.428571 | O49: =IF(L49="No","No",(L49*0.1)+(N49*M49)) -> 60.72 | P49: =IF(O49="No","No",O49+L49) -> 667.92
A50: 30 | B50: 5.9 | C50: ARETIERS | D50: =D49 -> TERREAL | E50: =X19 -> 20 | F50: =E50 -> 20 | G50: ml | H50: 18 | I50: /ml | J50: 0.15 | K50: 0.1 | L50: =IF(F50="No","No",((H50*F50)*(1+J50))*(K50+1)) -> 455.4 | N50: =500/7 -> 71.428571 | O50: =IF(L50="No","No",(L50*0.1)+(N50*M50)) -> 45.54 | P50: =IF(O50="No","No",O50+L50) -> 500.94
A51: 31 | B51: 6 | C51: NOUES | D51: =D50 -> TERREAL | E51: =Z19 -> 6 | F51: =E51 -> 6 | G51: ml | H51: 40 | I51: /ml | J51: 0.15 | K51: 0.1 | L51: =IF(F51="No","No",((H51*F51)*(1+J51))*(K51+1)) -> 303.6 | N51: =500/7 -> 71.428571 | O51: =IF(L51="No","No",(L51*0.1)+(N51*M51)) -> 30.36 | P51: =IF(O51="No","No",O51+L51) -> 333.96
A52: 32 | B52: 6.1 | L52: =SUM(L27:L51) -> 32362.457 | M52: =(SUM(M27:M51))/8 -> 42 | N52: jours | O52: =SUM(O27:O51) -> 26093.389 | P52: =SUM(P27:P51) -> 58455.846 | Q52: =P52/F48 -> 129.90188 | R52: /m²
A53: 33 | B53: 6.2 | M53: =M52/5 -> 8.4 | N53: semaines
A54: 34 | B54: 6.3
A55: 35 | B55: 6.4
A56: 36 | B56: 6.5
A57: 37 | B57: 6.6
A58: 38 | B58: 6.7
A59: 39 | B59: 6.8
A60: 40 | B60: 6.9
A61: 41 | B61: 7
A62: 42 | B62: 7.1
A63: 43 | B63: 7.2
A64: 44 | B64: 7.3
A65: 45 | B65: 7.4
... A71: 51 | B71: 8
B72: 8.1
B73: 8.2
B74: 8.3
B75: 8.4
B76: 8.5
B77: 8.6
B78: 8.7
B79: 8.8
B80: 8.9
B81: 9
B82: 9.1
B83: 9.2
... B159: 16.8

Sheet Feuille 3

Sheet Feuille 2
A3: def | B3: traitement | C3: section(mm) | D3: nbr | E3: qu | F3: prix | G3: revente | H3: quantitatif | I3: commande
M4: Longueur | N4: Matériau | O4: Type de tête | P4: Produit / Référence | Q4: Conditionnement | R4: Prix ~ € / unité
A5: OSSATURE DOUGLAS NAT. 45X95 RAB4F SEC 18 % | B5: E1 | C5: 45*95 | D5: 1 | E5: ml | F5: 2.9 | G5: =F5*1.27 -> 3.683 | M5: 40 mm | N5: Inox A2 | O5: Tête fraisée | P5: Vis bois Torx Inox 6×40 (Fixtout) | Q5: 100 pcs | R5: ~0,135 € (13,50 € /100)
A6: OSSATURE DOUGLAS NAT. 45X145 RAB4F SEC 18 % | B6: E1 | C6: 45*145 | D6: 1 | E6: ml | F6: 4.5 | G6: =F6*1.27 -> 5.715 | M6: 60 mm | N6: Inox A2 | O6: Tête fraisée | P6: 8 vis inox tête fraisée Torx Ø6 x L.60 mm | Q6: 8 pcs | R6: ~0,87 €/vis
A7: OSSATURE DOUGLAS NAT. 45X220 RAB4F SEC 18 % | B7: E1 | C7: 45*220 | D7: 1 | E7: ml | F7: 6.8 | G7: =F7*1.27 -> 8.636 | M7: 60 mm | N7: Acier zingué | O7: Tête fraisée Torx | P7: Vis à bois bichromatée tête fraisée Torx | Q7: Variable | R7: ~0,056 €*
A8: OSB3 12MM 2.50 X 1.25 PNX 3.125m2 | B8: E19 | C8: 1250*2500 | D8: 1 | E8: m² | F8: =ROUNDUP(95/5.5,0) -> 18 | G8: =F8*1.27 -> 22.86 | M8: 80 mm | N8: Acier | O8: Tête fraisée Torx | P8: 10 Vis Agglo Acier Tête Fraisée Torx 6x80mm - Coteka | Q8: 10 pcs | R8: ~0,50 €/vis
A9: PARE VAPEUR SALOLA AEROVAP SD18 - Rlx75m2 | D9: 75 | E9: m² | F9: 95 | G9: =F9*1.27 -> 120.65 | M9: 80 mm | N9: Inox A2 | O9: Tête fraisée Torx | P9: 100x Vis à bois tête fraisée en Acier inoxydable Torx V2A 6x80mm | Q9: 100 pcs | R9: ~0,24 €/vis
A10: BNR TR CL4 VERT - RABOTE 4 FACES section 45X145mm | B10: E19 | C10: 5.4 | D10: 1 | E10: ml | F10: 7 | G10: =F10*1.27 -> 8.89 | M10: 80 mm | N10: Acier zingué | O10: Demi-ronde Torx | P10: 90 vis acier tête demi‑ronde torx VISSAL | Q10: 90 pcs | R10: ~0,12 €/vis
A11: BNR TR CL4 VERT - RABOTE 4 FACES section 45X220mm | B11: E20 | C11: 5.4 | D11: 1 | E11: ml | F11: 7.3 | G11: =F11*1.27 -> 9.271 | M11: 100 mm | N11: Inox A2 | O11: Tête fraisée Torx | P11: entrepôt du bricolage — inox 50 pcs | Q11: ~24,95 € /50 | R11: ~0,50 €/vis
A12: LAINE DE BOIS SEMIN FLEX PLUS 1.22 x 0.565m ép. 145mm | B12: 505010 | C12: 1.22 | D12: 1 | E12: m² | F12: 13.5 | G12: =F12*1.27 -> 17.145 | M12: 100 mm | N12: Inox A2 | O12: Tête fraisée Torx | P12: prix-de-gros inox 100 pcs | Q12: 31,24 € /100 | R12: ~0,31 €/vis
A13: BARDAGE EPICEA TR CL3 MARRON - PROFIL LINE 125 20 x 125 MM | B13: 206002 | C13: 20*125 | D13: 1 | E13: m² | F13: 24 | G13: =F13*1.27 -> 30.48 | M13: 100 mm | N13: Acier galvanisé | O13: Tête fraisée Torx | P13: prix-de-gros galvanisée 100 pcs | Q13: 12,19 € /100 | R13: ~0,12 €/vis
A14: DELTA PROTEKT BANDE D'ARASE (sur chape) 25m x 0.25 RLX | D14: 25 | E14: ml | F14: 92 | G14: =F14*1.27 -> 116.84 | M14: 120 mm | N14: Acier galvanisé | O14: Tête fraisée Torx | P14: prix-de-gros galvanisée 100 pcs | Q14: 16,61 € /100 | R14: ~0,17 €/vis
A15: ECRAN R2 HPV 50/1,50M ELOS | D15: 75 | E15: m² | F15: 82 | G15: =F15*1.27 -> 104.14 | M15: 120 mm | N15: Inox A2 | O15: Tête fraisée Torx | P15: Sud Bois Vis pour Bois en Inox Classic 6x120 mm | Q15: 100 pcs | R15: ~0,22 €/vis
A16: Produit / Référence | B16: Matériau | C16: Longueur | F16: prix | M16: 140 mm | N16: (présent mais non listé commercialement)** | P16: Vis bois TX Turbodrive Premium 6x140 | Q16: 1 lot | R16: ~32,90 € (lot)
A17: Vis bois Torx Inox 6×40 (Fixtout) | B17: Inox A2 | C17: 40 mm | D17: 1 | E17: u | F17: 0.135 | G17: =F17+0.5 -> 0.635
A18: 8 vis inox tête fraisée Torx Ø6 x L.60 mm | B18: Inox A2 | C18: 60 mm | D18: 1 | E18: u | F18: 0.87 | G18: =F18+0.5 -> 1.37 | M18: Essence | N18: Section (mm) | O18: Usage principal | P18: Longueurs (m) | Q18: Prix ~ €/m linéaire (indicatif) | R18: Remarques
A19: Vis à bois bichromatée tête fraisée Torx | B19: Acier zingué | C19: 60 mm | D19: 1 | E19: u | F19: 0.56 | G19: =F19+0.5 -> 1.06 | M19: Résineux – Sapin / Épicéa | N19: 18×44 | O19: Liteaux | P19: 2,40–3,00 | Q19: ~0,40 € | R19: Bois tendre, standard Bricolage
A20: 10 Vis Agglo Acier Tête Fraisée Torx 6x80mm - Coteka | B20: Acier | C20: 80 mm | D20: 1 | E20: u | F20: 0.5 | G20: =F20+0.5 -> 1 | N20: 27×44 | O20: Liteaux renforcés | P20: 2,40–4,00 | Q20: ~0,60 € | R20: Ossature légère
A21: 100x Vis à bois tête fraisée en Acier inoxydable Torx V2A 6x80mm | B21: Inox A2 | C21: 80 mm | D21: 1 | E21: u | F21: 0.24 | G21: =F21+0.5 -> 0.74 | N21: 38×63 | O21: Ossature | P21: 2,40–5,00 | Q21: ~0,90 € | R21: Usage structure
A22: 90 vis acier tête demi‑ronde torx VISSAL | B22: Acier zingué | C22: 80 mm | D22: 1 | E22: u | F22: 0.12 | G22: =F22+0.5 -> 0.62 | N22: 45×70 | O22: Ossature | P22: 2,40–5,00 | Q22: ~1,10 € | R22: Standard maison bois
A23: entrepôt du bricolage — inox 50 pcs | B23: Inox A2 | C23: 100 mm | D23: 1 | E23: u | F23: 0.5 | G23: =F23+0.5 -> 1 | N23: 45×95 | O23: Solives | P23: 3,00–6,00 | Q23: ~1,50 € | R23: Solivage plancher
A24: prix-de-gros inox 100 pcs | B24: Inox A2 | C24: 100 mm | D24: 1 | E24: u | F24: 0.31 | G24: =F24+0.5 -> 0.81 | N24: 63×100 | O24: Solives | P24: 3,00–6,00 | Q24: ~2,20 € | R24: Charpente légère
A25: prix-de-gros galvanisée 100 pcs | B25: Acier galvanisé | C25: 100 mm | D25: 1 | E25: u | F25: 0.12 | G25: =F25+0.5 -> 0.62 | N25: 75×150 | O25: Poutres | P25: 3,00–6,00 | Q25: ~3,95 € | R25: Bois structurel
A26: prix-de-gros galvanisée 100 pcs | B26: Acier galvanisé | C26: 120 mm | D26: 1 | E26: u | F26: 0.17 | G26: =F26+0.5 -> 0.67 | N26: 100×200 | O26: Charpente | P26: 4,00–6,00 | Q26: ~7,00 € | R26: Poutre porteuse
A27: Sud Bois Vis pour Bois en Inox Classic 6x120 mm | B27: Inox A2 | C27: 120 mm | D27: 1 | E27: u | F27: 0.22 | G27: =F27+0.5 -> 0.72
A28: Vis bois TX Turbodrive Premium 6x140 | B28: (présent mais non listé commercialement)** | C28: 140 mm | D28: 1 | E28: u | F28: 0.33 | G28: =F28+0.5 -> 0.83 | M28: Résineux durables (Douglas) | N28: Section (mm) | O28: Usage principal | P28: Longueurs (m) | Q28: Prix ~ €/m linéaire (TTC) | R28: Source / Remarques
A29: Essence | C29: section(mm) | F29: prix | N29: 38 × 150 | O29: Solivette / petit madrier | P29: 3,60 m – 4,50 m | Q29: ~3,80 € TTC/m | R29: Arrivage Douglas sec – dimensions & prix HT ~3,20 € (≈3,84 € TTC) (Recyc'Eco)
A30: Résineux – Sapin / Épicéa | B30: C18 | C30: 18×44 | D30: 1 | E30: ml | F30: 0.4 | G30: =F30*1.3 -> 0.52 | N30: 38 × 200 | O30: Madrier charpente / coffrage | P30: ~2,00 m | Q30: ~5,75 € TTC/m | R30: Bois direct usine – madrier Douglas 38×200mm (Bois Direct Usine)
B31: C18 | C31: 27×44 | D31: 1 | E31: ml | F31: 0.6 | G31: =F31*1.3 -> 0.78 | N31: 45 × 70 | O31: Ossature légère | P31: 3–5 m (raboté possible) | Q31: ~1,80–2,50 € TTC/m | R31: Disponible chez négociants (raboté 45×70) (UneTerrasse.com)
B32: C18 | C32: 38×63 | D32: 1 | E32: ml | F32: 0.9 | G32: =F32*1.3 -> 1.17 | N32: 45 × 95 | O32: Ossature / mur MOB | P32: 2–5,10 m | Q32: ~4,00 € TTC/m | R32: Montant ossature Douglas Classe 2 (~4 €/m) (Matériaux Naturels)
B33: C18 | C33: 45×70 | D33: 1 | E33: ml | F33: 1.1 | G33: =F33*1.3 -> 1.43 | N33: 45 × 120 | O33: Ossature plus large | P33: 2–5,10 m | Q33: ~4,70–5,80 € TTC/m | R33: Ossature Douglas raboté promos (centralbois.fr)
B34: C18 | C34: 45×95 | D34: 1 | E34: ml | F34: 1.5 | G34: =F34*1.3 -> 1.95 | N34: 45 × 145 | O34: Ossature / structure | P34: 2–5,10 m | Q34: ~4,90–6,25 € TTC/m | R34: Raboté / promos - différents vendeurs (centralbois.fr)
B35: C18 | C35: 63×100 | D35: 1 | E35: ml | F35: 2.2 | G35: =F35*1.3 -> 2.86 | N35: 45 × 220 | O35: Gros ossature / meuble | P35: 3–5,10 m | Q35: ~8,80 € TTC/m | R35: Montant ossature Douglas Classe 2 (larges) (Matériaux Naturels)
B36: C18 | C36: 75×150 | D36: 1 | E36: ml | F36: 3.95 | G36: =F36*1.3 -> 5.135 | N36: 50 × 150 | O36: Bastaing / solive | P36: 3–6 m | Q36: ~4,82–4,95 € TTC/m | R36: Woodlife – Douglas madrier (50×150) (woodlife-scierie.fr)
B37: C18 | C37: 100×200 | D37: 1 | E37: ml | F37: 7 | G37: =F37*1.3 -> 9.1 | N37: 63 × 175 | O37: Solive / charpente | P37: 3–6 m | Q37: ~8,40–8,40 € TTC/m | R37: Tambours madrier Douglas 63×175 (woodlife-scierie.fr)
C38: No | H38: No | N38: 75 × 200 | O38: Poutre structurelle | P38: 3–6 m | Q38: ~10,24 –10,85 € TTC/m | R38: Madrier Douglas 75×200 (woodlife-scierie.fr)
A39: Résineux durables (Douglas) | B39: C24 | C39: 38 × 150 | D39: 1 | E39: ml | F39: 3.8 | G39: =F39*1.3 -> 4.94 | N39: 75 × 225 | O39: Poutre charpente lourde | P39: 5–6 m | Q39: ~11,63–12,22 € TTC/m | R39: Douglas madrier 75×225 (woodlife-scierie.fr)
B40: C24 | C40: 38 × 200 | D40: 1 | E40: ml | F40: 5.75 | G40: =F40*1.3 -> 7.475 | N40: 320 × 90 | O40: Poutre lamellé-collé | P40: 6,00 m | Q40: ~49,82 € TTC/m | R40: Poutre lamellé-collé Douglas segmentée (Partedis Bois et Matériaux)
B41: C24 | C41: 45 × 70 | D41: 1 | E41: ml | F41: 2.5 | G41: =F41*1.3 -> 3.25
B42: C24 | C42: 45 × 95 | D42: 1 | E42: ml | F42: 4 | G42: =F42*1.3 -> 5.2 | M42: Type de tuile | N42: Modèle courant (exemples) | O42: Tuiles / m² | P42: Prix ~ €/m² | Q42: Pente mini | R42: Couleurs disponibles
B43: C24 | C43: 45 × 120 | D43: 1 | E43: ml | F43: 5.8 | G43: =F43*1.3 -> 7.54 | M43: Marseille mécanique | N43: Marseille Monier, Cotto 14 | O43: 10,5 – 11,5 | P43: 22 – 35 € | Q43: ≥ 30 % | R43: Rouge, rosé, vieilli, brun
B44: C24 | C44: 45 × 145 | D44: 1 | E44: ml | F44: 6.25 | G44: =F44*1.3 -> 8.125 | M44: PV10 / Petite moule | N44: PV10 Edilians | O44: 13 – 15 | P44: 28 – 40 € | Q44: ≥ 25 % | R44: Rouge nuancé, flammé
B45: C24 | C45: 45 × 220 | D45: 1 | E45: ml | F45: 8.8 | G45: =F45*1.3 -> 11.44 | M45: Romane mécanique | N45: Romane Canal Terreal | O45: 9,5 – 11 | P45: 25 – 38 € | Q45: ≥ 30 % | R45: Rouge, sablé, vieilli
B46: C24 | C46: 50 × 150 | D46: 1 | E46: ml | F46: 4.95 | G46: =F46*1.3 -> 6.435 | M46: Canal mécanique | N46: Canal Midi, Languedocienne | O46: 11 – 13 | P46: 20 – 32 € | Q46: ≥ 27 % | R46: Rouge, rosé, flammé
B47: C24 | C47: 63 × 175 | D47: 1 | E47: ml | F47: 8.4 | G47: =F47*1.3 -> 10.92 | M47: Double canal | N47: DCL Terreal | O47: 10 – 12 | P47: 30 – 45 € | Q47: ≥ 25 % | R47: Rouge naturel, patiné
B48: C24 | C48: 75 × 200 | D48: 1 | E48: ml | F48: 10.85 | G48: =F48*1.3 -> 14.105
B49: C24 | C49: 75 × 225 | D49: 1 | E49: ml | F49: 12.22 | G49: =F49*1.3 -> 15.886 | M49: Élément | N49: Prix indicatif
B50: C24 | C50: 320 × 90 | D50: 1 | E50: ml | F50: 49.82 | G50: =F50*1.3 -> 64.766 | M50: Faîtière | N50: 15 – 30 € / ml
A51: Type de tuile | C51: Tuiles / m² | M51: Rives | N51: 8 – 15 € / pièce
A52: MONIER - Marseille mécanique | C52: 11.5 | D52: 1 | E52: m² | F52: 35 | G52: =F52*1.3 -> 45.5 | M52: Chatière | N52: 25 – 60 €
A53: EDILIANS - PV10 / Petite moule | C53: 15 | D53: 1 | E53: m² | F53: 40 | G53: =F53*1.3 -> 52 | M53: Rencontre / arêtier | N53: 35 – 80 €
A54: TERREAL - Romane mécanique | C54: 11 | D54: 1 | E54: m² | F54: 38 | G54: =F54*1.3 -> 49.4
A55: TERREAL - Canal mécanique, Langedocienne | C55: 13 | D55: 1 | E55: m² | F55: 32 | G55: =F55*1.3 -> 41.6 | M55: Produit / Écran HPV | N55: Type / Classe | O55: Surface (rouleau) | P55: Poids indicatif | Q55: Prix indicatif | R55: Remarques clés
A56: TERREAL - Double canal | C56: 12 | D56: 1 | E56: m² | F56: 45 | G56: =F56*1.3 -> 58.5 | M56: Écran sous‑toiture HPVR2 Maxi Plus 150 g/m² | N56: R2 – HPV standard | O56: 75 m² (1,5×50 m) | P56: ~150 g/m² | Q56: ~148,50 € | R56: Bon compromis performance/ᵉ prix, adapté tuiles & ardoises
A57: TERREAL - DC12 Double Canal 12 | C57: 12 | D57: 1 | E57: m² | F57: 25 | G57: =F57*1.3 -> 32.5 | M57: ARTISANMAT HPVR2 Strong 160 g/m² | N57: R2 – HPV renforcé | O57: 75 m² (1,5×50 m) | P57: ~160 g/m² | Q57: ~168,74 € | R57: Plus résistant mécaniquement (pose en conditions difficiles)
A58: TERREAL – Tuile plate Ardoisé 1EL | C58: 27 | D58: 1 | E58: m² | F58: 56.8 | G58: =F58*1.3 -> 73.84 | M58: ARTISANMAT HPVR3 Comfort 220 g/m² | N58: R3 – HPV haute performance | O58: 75 m² | P58: ~220 g/m² | Q58: ~200,81 € | R58: Très haute résistance, idéal pentes faibles / conditions sévères
A59: TERREAL – Tuile plate Ségala 1P20 | C59: 25 | D59: 1 | E59: m² | F59: =(F58+F57)/2 -> 40.9 | G59: =F59*1.3 -> 53.17 | M59: TERREAL Écran EsTerre HPV R3 | N59: R3 – HPV pro | O59: ~75 m² | P59: ~160 g/m²* | Q59: ~276,13 € | R59: Version pro certifiée, pour grandes toitures & faible pente
A60: EDILIANS – Omega 10 | C60: 10 | D60: 1 | E60: m² | F60: 29.3 | G60: =F60*1.3 -> 38.09 | M60: STRATEC II F 75 m² | N60: Expression HPV | O60: 75 m² | P60: ~160 g/m² | Q60: ~91,80 € | R60: Polyvalent, norme EN 13859
A61: EDILIANS – PV10 Huguenot | C61: 10 | D61: 1 | E61: m² | F61: 28.4 | G61: =F61*1.3 -> 36.92 | M61: Écran HPV R2 1,50×50 m | N61: R2 – HPV | O61: 75 m² | P61: ~150 g/m² | Q61: ~85,90 € | R61: Version économique, conforme DTU
A62: EDILIANS – H14 (grand moule) | C62: 13 | D62: 1 | E62: m² | F62: 39.7 | G62: =F62*1.3 -> 51.61 | M62: QEM HPV HYGROV+ triple couches | N62: HPV triple couches | O62: 75 m² | P62: – | Q62: ~41,58 € | R62: Option économique pour toits ventilés
A63: EDILIANS – Méridionale | C63: 13.5 | D63: 1 | E63: m² | F63: 29 | G63: =F63*1.3 -> 37.7 | M63: QEM HPV HYGROV+ haute résistance UV | N63: HPV haute résistance | O63: 75 m² | P63: – | Q63: ~119,99 € | R63: Meilleur comportement UV & mécanique
C64: No
A65: SAPIN TR CL2 - CE - C18 / BRUT DE SCIAGE 8x18 CM | B65: CL2/E1 | C65: 80/180 | D65: 1 | E65: ml | F65: =236/42 -> 5.6190476 | G65: =F65*1.3 -> 7.3047619
A66: SAPIN TR CL2 - CE - C18 / BRUT DE SCIAGE 8x11 CM | B66: CL2/E2 | C66: 80/110 | D66: 1 | E66: ml | F66: =62/18 -> 3.4444444 | G66: =F66*1.3 -> 4.4777778
A67: VOLIGES 15mm TR2 TTL ( toutes largeurs ) | B67: E30 | C67: 15/TL | D67: 1 | E67: m² | F67: 4.95 | G67: =F67*1.3 -> 6.435
A68: VOLIGES BNB (épicéa) MI-BOIS section 15x195mm RABOTE 1 FACE | B68: E31 | C68: 15/195 | D68: 1 | E68: m² | F68: 13.5 | G68: =F68*1.3 -> 17.55
A69: KVH EPICEA ABOUTE C24 section 8X18 cm | B69: C18 | C69: 80/180 | D69: 1 | E69: ml | F69: 8.5 | G69: =F69*1.3 -> 11.05
A70: CONTRE-LITEAUX sapin 2X4cm ( par paquet ) | B70: CL2/E1 | C70: 20/40 | D70: 1 | E70: ml | F70: 0.45 | G70: =F70*1.3 -> 0.585 | M70: Référence / Produit | N70: Marque | O70: Nombre au m² | P70: Prix unitaire | Q70: Prix au m² estimé
A71: LITEAUX sapin 3X4cm | B71: CL2/E2 | C71: 30/40 | D71: 1 | E71: ml | F71: 0.48 | G71: =F71*1.3 -> 0.624 | M71: TERREAL – DC12 Double Canal 12 | N71: TERREAL | O71: ~12 /m² (grand moule sud) (Bricoman) | P71: ~1,56 €/pièce (Bricoman) | Q71: ~18,7 €/m²
M72: TERREAL – Tuile plate Ardoisé 1EL | N72: TERREAL | O72: ~27 /m² (Leroy Merlin) | P72: ~2,10 €/pièce (Leroy Merlin) | Q72: ~56,7 €/m²
M73: TERREAL – Tuile plate Ségala 1P20 | N73: TERREAL | O73: ~? (standard petite tuile plate ~25 /m²) | P73: ~990,59 € palette | Q73: voir prix pro
M74: EDILIANS – Omega 10 | N74: EDILIANS | O74: 10 /m² (Bricoman) | P74: ~2,93 €/pièce (Bricoman) | Q74: ~29,3 €/m²
M75: EDILIANS – PV10 Huguenot | N75: EDILIANS | O75: 10 /m² (Bricoman) | P75: ~2,84 €/pièce (Bricoman) | Q75: ~28,4 €/m²
M76: EDILIANS – H14 (grand moule) | N76: EDILIANS | O76: 13 /m² (Bricoman) | P76: ~3,05 €/pièce (Bricoman) | Q76: ~39,7 €/m²
M77: EDILIANS – Méridionale | N77: EDILIANS | O77: 13,5 /m² (Bricoman) | P77: ~2,15 €/pièce (Bricoman) | Q77: ~29,0 €/m²
